[
  {
    "id": "1125df0b-772a-43e4-aa73-003902c00379",
    "title": "Owner Panel & Empty State UX",
    "description": "- Resolved 'Not Authorized' message when owners had no printers.\n- Added prompt to create a new listing.\n- Added friendly message on the printers page when no listings are available.",
    "created_at": "2025-06-17T00:12:18.000Z"
  },
  {
    "id": "e33841df-68bb-4c0f-9927-2e1070f1f569",
    "title": "Soft Delete System",
    "description": "- Implemented soft delete for printers, preserving historical bookings and visibility.\n- Viewing deleted printers no longer hangs and shows a deleted label.\n- Fixed 'Unknown Printer' display and hid booking button for deleted listings.",
    "created_at": "2025-06-16T22:45:00.000Z"
  },
  {
    "id": "67ddf3f6-dca4-47af-adb8-14967d46139f",
    "title": "Owner Panel Enhancements",
    "description": "- Edit buttons in the Owner Panel now link to the printer edit screen.\n- Added printer availability controls and booking status management for owners.",
    "created_at": "2025-06-16T21:57:30.000Z"
  },
  {
    "id": "43acb14c-7639-4204-af1a-bc0a122ab13a",
    "title": "Dashboard Launch",
    "description": "- Added a fully functional Owner Panel with printer and booking summaries.\n- Built the My Printers page for managing listings.\n- Populated the Profile page with user details, account actions, and upcoming bookings.",
    "created_at": "2025-06-14T02:46:00.000Z"
  },
  {
    "id": "5777d4b1-f16b-4160-ad0f-011b48ca9621",
    "title": "Initial Public Release",
    "description": "- First public version of RentAPrint.\n- Resolved booking issues and improved printer search.",
    "created_at": "2025-06-14T02:43:02.000Z"
  },
  {
    "id": "af9ce1d7-d105-4eca-9a02-6ee1b425ea99",
    "title": "Major Updates",
    "description": "- Improved booking cancellation errors.\n- Cleaned duplicate components.\n- Clarified test instructions and fixed environment example.",
    "created_at": "2024-01-01T00:00:00.000Z"
  }
]
